{
  "posts": [
    {
      "postId": 1,
      "title": "First Post",
      "body": "This is the first post",
      "image": "assets/image1.jpeg",
      "isFavourite": false,
       "isEditMode": false
    },
    {
      "postId": 2,
      "title": "Second Post",
      "body": "This is the Second post",
      "image": "assets/image1.jpeg",
      "isFavourite": false,
      "isEditMode": false
    },
    {
      "postId": 3,
      "title": "Third Post",
      "body": "This is the Third post",
      "image": "src/assets/image1.jpeg",
      "isFavourite": false, 
      "isEditMode": false
    },
    {
      "postId": 4,
      "title": "Fourth Post",
      "body": "This is the Fourth post",
      "image": "assets/image1.jpeg",
      "isFavourite": false,
      "isEditMode": false
    },
    {
      "postId": 5,
      "title": "Fifth Post",
      "body": "This is the Fifth post",
      "image": "assets/image1.jpeg",
      "isFavourite": false,
      "isEditMode": false
    }
  ]
}
